nanodjango/__init__.py
nanodjango/__main__.py
nanodjango/app.py
nanodjango/app_meta.py
nanodjango/asgi.py
nanodjango/commands.py
nanodjango/defer.py
nanodjango/exceptions.py
nanodjango/hookspecs.py
nanodjango/settings.py
nanodjango/templatetags.py
nanodjango/urls.py
nanodjango/views.py
nanodjango/wsgi.py
nanodjango/contrib/__init__.py
nanodjango/contrib/django_browser_reload.py
nanodjango/contrib/django_distill.py
nanodjango/contrib/django_ninja.py
nanodjango/convert/__init__.py
nanodjango/convert/converter.py
nanodjango/convert/objects.py
nanodjango/convert/reference.py
nanodjango/convert/utils.py
nanodjango/django_glue/__init__.py
nanodjango/django_glue/apps.py
nanodjango/django_glue/db.py
nanodjango/testing/__init__.py
nanodjango/testing/utils.py
nanodjango-0.13.0.dist-info/licenses/LICENSE.md
nanodjango-0.13.0.dist-info/METADATA
nanodjango-0.13.0.dist-info/WHEEL
nanodjango-0.13.0.dist-info/entry_points.txt
nanodjango-0.13.0.dist-info/top_level.txt
nanodjango-0.13.0.dist-info/RECORD
