Metadata-Version: 2.4
Name: nanodjango
Version: 0.13.0
Summary: Run Django models and views from a single file, and convert it to a full project.
Author-email: Richard Terry <code@radiac.net>
Project-URL: Homepage, https://radiac.net/projects/nanodjango/
Project-URL: Documentation, https://nanodjango.readthedocs.io/en/latest/
Project-URL: Changelog, https://nanodjango.readthedocs.io/en/latest/changelog.html
Project-URL: Repository, https://github.com/radiac/nanodjango
Project-URL: Issues, https://github.com/radiac/nanodjango/issues
Keywords: django
Classifier: Development Status :: 4 - Beta
Classifier: Framework :: Django
Classifier: License :: OSI Approved :: BSD License
Classifier: Programming Language :: Python :: 3
Classifier: Operating System :: OS Independent
Requires-Python: >=3.8
License-File: LICENSE.md
Requires-Dist: black
Requires-Dist: click
Requires-Dist: Django>=5.2
Requires-Dist: django-ninja
Requires-Dist: gunicorn
Requires-Dist: isort
Requires-Dist: pluggy
Requires-Dist: uvicorn
Requires-Dist: whitenoise
Provides-Extra: static
Requires-Dist: django-nanopages; extra == "static"
Requires-Dist: django-distill; extra == "static"
Provides-Extra: full
Requires-Dist: django-nanopages; extra == "full"
Requires-Dist: django-distill; extra == "full"
Dynamic: license-file
